Metadata-Version: 2.1
Name: fastapi-opentracing
Version: 0.3.3
Summary: fastapi opentracing middleware works with istio
Home-page: https://github.com/wesdu/fastapi-opentracing
Author: Du Wei
Author-email: pandorid@gmail.com
License: UNKNOWN
Keywords: fastapi,istio,k8s,opentracing
Platform: UNKNOWN
Classifier: Programming Language :: Python :: 3
Classifier: Programming Language :: Python :: 3.7
Classifier: License :: OSI Approved :: MIT License
Classifier: Operating System :: OS Independent
